{
	"productName": "onelauncher",
	"version": "0.0.0",
	"identifier": "org.polyfrost.launcher",
	"app": {
		"withGlobalTauri": true,
		"security": {
			"csp": "default-src 'self'; connect-src https://modrinth.com https://*.modrinth.com https://polyfrost.org https://*.polyfrost.org https://*.cloudflare.com https://api.mclo.gs; img-src tauri: https: data: blob: 'unsafe-inline' asset: https://asset.localhost; script-src https://*.cloudflare.com 'self'; frame-src https://*.cloudflare.com https://www.youtube.com https://www.youtube-nocookie.com https://discord.com 'self'; style-src unsafe-inline 'self'",
			"capabilities": []
		},
		"windows": [
			{
				"title": "OneLauncher",
				"width": 1280,
				"height": 802,
				"minWidth": 1080,
				"minHeight": 600,
				"resizable": true,
				"center": true,
				"decorations": false,
				"shadow": true
			}
		]
	},
	"build": {
		"beforeDevCommand": "pnpm dev",
		"beforeBuildCommand": "pnpm build",
		"frontendDist": "../dist",
		"devUrl": "http://localhost:8001"
	},
	"bundle": {
		"active": true,
		"targets": "all",
		"category": "Game",
		"icon": [
			"icons/32x32.png",
			"icons/128x128.png",
			"icons/128x128@2x.png",
			"icons/icon.icns",
			"icons/icon.ico"
		],
		"copyright": "Polyfrost",
		"fileAssociations": [
			{
				"ext": ["mrpack"],
				"description": ""
			}
		]
	},
	"plugins": {}
}
